{
  "title": "🐄 Kuh-Leben-Simulator",
  "startCows": "Startende Kühe (#)",
  "grassGrow": "Graswachstumszeit (s)",
  "eatTime": "Essenszeit (s)",
  "hungerLimit": "Überleben ohne Futter (s)",
  "reproLabel": "Fortpflanzungschance (%):",
  "illnessChance": "Krankheitschance (%)",
  "illnessDeath": "Krankheitssterblichkeit (%)",
  "maxAge": "Maximales Alter. 0 = aus (s)",
  "status": "Status",
  "elapsed": "Verstrichene Zeit",
  "current": "Aktuelle Kühe",
  "grass": "Verfügbares Gras",
  "maxCows": "Maximale Kuhanzahl jemals",
  "minCows": "Minimale Kuhanzahl jemals",
  "oldest": "Älteste Kuh",
  "born": "Gesamtgeburten",
  "deadHunger": "Todesfälle Hunger",
  "deadIllness": "Todesfälle Krankheit",
  "deadAge": "Todesfälle Alter",
  "btnPause": "Pausieren",
  "btnResume": "Fortsetzen",
  "btnReset": "Zurücksetzen",
  "btnLang": "Sprache Laden",
  "statusRunning": "Läuft",
  "statusPaused": "Pausiert",
  "graphMax": "Maximalwert ist: ",
  "btnLoadCfg": "Konfiguration Laden",
  "btnSaveCfg": "Konfiguration Speichern",
  "legHungry": "Hungrige Kuh",
  "legEating": "Essende Kuh",
  "legSick": "Kranke Kuh",
  "legGrass": "Gras",
  "legEaten": "Gegessenes Gras",
  "legStone": "Steine",
  "legWater": "Wasser"
}

